setup.py
zipdbm.py
zipdbm.egg-info/PKG-INFO
zipdbm.egg-info/SOURCES.txt
zipdbm.egg-info/dependency_links.txt
zipdbm.egg-info/top_level.txt