Metadata-Version: 1.1
Name: zipdbm
Version: 1.0.0
Summary: Dict-style DBM based on zipfile.
Home-page: https://github.com/imbolc/zipdbm
Author: Imbolc
Author-email: imbolc@imbolc.name
License: ISC
Platform: UNKNOWN
Classifier: Development Status :: 4 - Beta
Classifier: Intended Audience :: Developers
Classifier: License :: OSI Approved :: ISC License (ISCL)
